onecondition/__init__.py
onecondition/test.py
onecondition/validate.py
onecondition-1.1.15.dist-info/LICENSE
onecondition-1.1.15.dist-info/WHEEL
onecondition-1.1.15.dist-info/METADATA
onecondition-1.1.15.dist-info/RECORD
