Metadata-Version: 2.1
Name: onecondition
Version: 1.1.15
Summary: An ultra-lightweight package for validating single conditions.
Author-email: Ella Jameson <ellagjameson@gmail.com>
Requires-Python: >=3.7
Classifier: Development Status :: 5 - Production/Stable
Classifier: License :: OSI Approved :: GNU General Public License v3 or later (GPLv3+)
Classifier: Programming Language :: Python
Classifier: Programming Language :: Python :: 3
Classifier: Programming Language :: Python :: 3.7
Classifier: Programming Language :: Python :: 3.8
Classifier: Programming Language :: Python :: 3.9
Classifier: Programming Language :: Python :: 3.10
Classifier: Programming Language :: Python :: 3.11
Classifier: Programming Language :: Python :: 3.12
Classifier: Programming Language :: Python :: 3 :: Only
Project-URL: documentation, https://onecondition.readthedocs.io/en/latest/index.html
Project-URL: homepage, https://github.com/nimaid/python-onecondition
Project-URL: issues, https://github.com/nimaid/python-onecondition/issues
Project-URL: repository, https://github.com/nimaid/python-onecondition
